popleave/__init__.py
popleave/popleave.py
popleave/template.docx
popleave-0.1.4.dist-info/entry_points.txt
popleave-0.1.4.dist-info/LICENSE
popleave-0.1.4.dist-info/METADATA
popleave-0.1.4.dist-info/WHEEL
popleave-0.1.4.dist-info/RECORD
