Metadata-Version: 2.1
Name: popleave
Version: 0.1.4
Summary: Populates Leave Forms from the Command Line
License: GPL-3.0-or-later
Author: Alex Drysdale
Author-email: alexander.drysdale@wales.nhs.uk
Requires-Python: >=3.12,<4.0
Classifier: License :: OSI Approved :: GNU General Public License v3 or later (GPLv3+)
Classifier: Programming Language :: Python :: 3
Classifier: Programming Language :: Python :: 3.12
Requires-Dist: appdirs (>=1.4.4,<2.0.0)
Requires-Dist: python-docx (>=1.1.2,<2.0.0)
